ab_core/dependency/__init__.py
ab_core/dependency/default.py
ab_core/dependency/depends.py
ab_core/dependency/injection.py
ab_core/dependency/sentinel.py
ab_core/dependency/singleton.py
ab_core/dependency/types.py
ab_core/dependency/utils.py
ab_core/dependency/loaders/__init__.py
ab_core/dependency/loaders/base.py
ab_core/dependency/loaders/environment.py
ab_core/dependency/loaders/environment_object.py
ab_core/dependency/loaders/template.py
ab_core/dependency/pydanticize/__init__.py
ab_core/dependency/pydanticize/pydanticize.py
ab_core/dependency/pydanticize/cast/__init__.py
ab_core/dependency/pydanticize/cast/helpers.py
ab_core/dependency/pydanticize/cast/adaptors/__init__.py
ab_core/dependency/pydanticize/cast/adaptors/attrs.py
ab_core/dependency/pydanticize/cast/adaptors/base.py
ab_core/dependency/pydanticize/cast/adaptors/unset.py
ab_core/dependency/schema/__init__.py
ab_core/dependency/schema/loader_type.py
ab_dependency-0.2.0.dist-info/METADATA
ab_dependency-0.2.0.dist-info/WHEEL
ab_dependency-0.2.0.dist-info/licenses/LICENSE
ab_dependency-0.2.0.dist-info/RECORD
