Metadata-Version: 2.4
Name: ab-dependency
Version: 0.2.0
Author-email: Matthew Coulter <53892067+mattcoulter7@users.noreply.github.com>
License-File: LICENSE
Requires-Python: <4,>=3.12
Requires-Dist: deepdiff<9,>=8.5.0
Requires-Dist: generic-preserver<0.2,>=0.1.4
Requires-Dist: pydantic-settings<3,>=2.10.1
Requires-Dist: pydantic<3,>=2.11.7
Provides-Extra: all
Requires-Dist: attrs>=22.2.0; extra == 'all'
Provides-Extra: attrs-plugin
Requires-Dist: attrs>=22.2.0; extra == 'attrs-plugin'
Provides-Extra: fastapi
Requires-Dist: fastapi>=0.78.0; extra == 'fastapi'
